sasoptpy/__init__.py
sasoptpy/actions.py
sasoptpy/config.py
sasoptpy/math.py
sasoptpy/structure.py
sasoptpy/version.py
sasoptpy/abstract/__init__.py
sasoptpy/abstract/condition.py
sasoptpy/abstract/implicit_variable.py
sasoptpy/abstract/math.py
sasoptpy/abstract/parameter.py
sasoptpy/abstract/parameter_group.py
sasoptpy/abstract/range.py
sasoptpy/abstract/set.py
sasoptpy/abstract/set_iterator.py
sasoptpy/abstract/shadow.py
sasoptpy/abstract/util.py
sasoptpy/abstract/statement/__init__.py
sasoptpy/abstract/statement/assignment.py
sasoptpy/abstract/statement/cofor_loop.py
sasoptpy/abstract/statement/create_data.py
sasoptpy/abstract/statement/drop_restore.py
sasoptpy/abstract/statement/fix_unfix.py
sasoptpy/abstract/statement/for_loop.py
sasoptpy/abstract/statement/if_else.py
sasoptpy/abstract/statement/literal.py
sasoptpy/abstract/statement/objective.py
sasoptpy/abstract/statement/print.py
sasoptpy/abstract/statement/read_data.py
sasoptpy/abstract/statement/solve.py
sasoptpy/abstract/statement/statement_base.py
sasoptpy/core/__init__.py
sasoptpy/core/constraint.py
sasoptpy/core/constraint_group.py
sasoptpy/core/expression.py
sasoptpy/core/group.py
sasoptpy/core/model.py
sasoptpy/core/objective.py
sasoptpy/core/util.py
sasoptpy/core/variable.py
sasoptpy/core/variable_group.py
sasoptpy/interface/__init__.py
sasoptpy/interface/util.py
sasoptpy/interface/format/mps_format.py
sasoptpy/interface/format/optmodel_format.py
sasoptpy/interface/solver/cas_mediator.py
sasoptpy/interface/solver/mediator.py
sasoptpy/interface/solver/sas_mediator.py
sasoptpy/libs/__init__.py
sasoptpy/libs/numpy.py
sasoptpy/libs/pandas.py
sasoptpy/session/__init__.py
sasoptpy/session/workspace.py
sasoptpy/util/__init__.py
sasoptpy/util/package_utils.py
sasoptpy/util/user_utils.py
sasoptpy-1.0.5.dist-info/LICENSE
sasoptpy-1.0.5.dist-info/METADATA
sasoptpy-1.0.5.dist-info/WHEEL
sasoptpy-1.0.5.dist-info/top_level.txt
sasoptpy-1.0.5.dist-info/RECORD
