Metadata-Version: 2.1
Name: sasoptpy
Version: 1.0.5
Summary: sasoptpy: SAS Optimization Interface for Python
Home-page: https://github.com/sassoftware/sasoptpy
Author: Sertalp B. Cay (SAS Institute)
Author-email: Sertalp.Cay@sas.com
License: Apache v2.0
Platform: UNKNOWN
Classifier: Programming Language :: Python :: 3
Classifier: License :: OSI Approved :: Apache Software License
Classifier: Operating System :: OS Independent
Classifier: Topic :: Scientific/Engineering :: Mathematics
Requires-Python: >=3.7
License-File: LICENSE
Requires-Dist: pandas
Requires-Dist: swat
Requires-Dist: saspy
Requires-Dist: numpy
